{"about-me.md":"CX-moW_v","example.md":"D7PAdfqF","hobby_index.md":"IRJuJR54","hobby_novel_writing_index.md":"CQ0Zo96k","hobby_video_editing_index.md":"BPbCMpvy","index.md":"BnlyLFa5","jobs_history-entebbe.md":"lbwc_yjp","jobs_index.md":"BeG9Vcqb","jobs_jokes.md":"YSlQb4no","jobs_notes-holiday.md":"B2y8jb85","jobs_notes-jobs.md":"Dr82gC9j","jobs_notes-lifeos.md":"N3Ki5jdi","jobs_notes-lose-weight.md":"CD5Zu8jd","jobs_notes-origin.md":"DFwuiURP","jobs_notes-perfectionist.md":"Ceql7Lhm","jobs_summary.md":"C-Olr7bR"}
